{
  "('Property', 'US\/Canada')": {
    "0": "Mediterranean Avenue",
    "1": "Baltic Avenue",
    "2": "Reading RR",
    "3": "Oriental Avenue",
    "4": "Vermont Avenue",
    "5": "Connecticut Avenue",
    "6": "St. Charles Place",
    "7": "Electric Company",
    "8": "States Avenue",
    "9": "Virginia Avenue",
    "10": "Pennsylvania RR",
    "11": "St. James Place",
    "12": "Tennessee Avenue",
    "13": "New York Avenue",
    "14": "Kentucky Avenue",
    "15": "Indiana Avenue",
    "16": "Illinois Avenue",
    "17": "B&O RR",
    "18": "Atlantic Avenue",
    "19": "Ventnor Avenue",
    "20": "Water Works",
    "21": "Marvin Gardens",
    "22": "Pacific Avenue",
    "23": "North Carolina Avenue",
    "24": "Pennsylvania Avenue",
    "25": "Short Line",
    "26": "Park Place",
    "27": "Boardwalk"
  },
  "('Property', 'UK\/International')": {
    "0": "Old Kent Road",
    "1": "Whitechapel Road",
    "2": "Kings Cross Station",
    "3": "The Angel, Islington",
    "4": "Euston Road",
    "5": "Pentonville Road",
    "6": "Pall Mall",
    "7": "Electric Company",
    "8": "Whitehall",
    "9": "Northumberland Avenue",
    "10": "Marylebone Station",
    "11": "Bow Street",
    "12": "Marlborough Street",
    "13": "Vine Street",
    "14": "Strand",
    "15": "Fleet Street",
    "16": "Trafalgar Square",
    "17": "Fenchurch St Station",
    "18": "Leicester Square",
    "19": "Coventry Street",
    "20": "Water Works",
    "21": "Piccadilly",
    "22": "Regent Street",
    "23": "Oxford Street",
    "24": "Bond Street",
    "25": "Liverpool Street Station",
    "26": "Park Lane",
    "27": "Mayfair"
  },
  "('Cost', 'Cost')": {
    "0": 60,
    "1": 60,
    "2": 200,
    "3": 100,
    "4": 100,
    "5": 120,
    "6": 140,
    "7": 150,
    "8": 140,
    "9": 160,
    "10": 200,
    "11": 180,
    "12": 180,
    "13": 200,
    "14": 220,
    "15": 220,
    "16": 240,
    "17": 200,
    "18": 260,
    "19": 260,
    "20": 150,
    "21": 280,
    "22": 300,
    "23": 300,
    "24": 320,
    "25": 200,
    "26": 350,
    "27": 400
  },
  "('Per House\/Hotel Cost', 'Per House\/Hotel Cost')": {
    "0": 50,
    "1": 50,
    "2": 0,
    "3": 50,
    "4": 50,
    "5": 50,
    "6": 100,
    "7": 0,
    "8": 100,
    "9": 100,
    "10": 0,
    "11": 100,
    "12": 100,
    "13": 100,
    "14": 150,
    "15": 150,
    "16": 150,
    "17": 0,
    "18": 150,
    "19": 150,
    "20": 0,
    "21": 150,
    "22": 200,
    "23": 200,
    "24": 200,
    "25": 0,
    "26": 200,
    "27": 200
  },
  "('Rent', 'Site')": {
    "0": "2",
    "1": "4",
    "2": "25 if 1 owned, 50 if 2 owned, 100 if 3 owned, 200 if all 4 owned",
    "3": "6",
    "4": "6",
    "5": "8",
    "6": "10",
    "7": "4\u00d7dice if 1 owned, 10\u00d7dice if both owned",
    "8": "10",
    "9": "12",
    "10": "25 if 1 owned, 50 if 2 owned, 100 if 3 owned, 200 if all 4 owned",
    "11": "14",
    "12": "14",
    "13": "16",
    "14": "18",
    "15": "18",
    "16": "20",
    "17": "25 if 1 owned, 50 if 2 owned, 100 if 3 owned, 200 if all 4 owned",
    "18": "22",
    "19": "22",
    "20": "4\u00d7dice if 1 owned, 10\u00d7dice if both owned",
    "21": "24[1]",
    "22": "26",
    "23": "26",
    "24": "28",
    "25": "25 if 1 owned, 50 if 2 owned, 100 if 3 owned, 200 if all 4 owned",
    "26": "35",
    "27": "50"
  },
  "('Rent', 'Site with colour set')": {
    "0": "4",
    "1": "8",
    "2": "25 if 1 owned, 50 if 2 owned, 100 if 3 owned, 200 if all 4 owned",
    "3": "12",
    "4": "12",
    "5": "16",
    "6": "20",
    "7": "4\u00d7dice if 1 owned, 10\u00d7dice if both owned",
    "8": "20",
    "9": "24",
    "10": "25 if 1 owned, 50 if 2 owned, 100 if 3 owned, 200 if all 4 owned",
    "11": "28",
    "12": "28",
    "13": "32",
    "14": "36",
    "15": "36",
    "16": "40",
    "17": "25 if 1 owned, 50 if 2 owned, 100 if 3 owned, 200 if all 4 owned",
    "18": "44",
    "19": "44",
    "20": "4\u00d7dice if 1 owned, 10\u00d7dice if both owned",
    "21": "48",
    "22": "52",
    "23": "52",
    "24": "56",
    "25": "25 if 1 owned, 50 if 2 owned, 100 if 3 owned, 200 if all 4 owned",
    "26": "70",
    "27": "100"
  },
  "('Rent', '1 house')": {
    "0": "10",
    "1": "20",
    "2": "25 if 1 owned, 50 if 2 owned, 100 if 3 owned, 200 if all 4 owned",
    "3": "30",
    "4": "30",
    "5": "40",
    "6": "50",
    "7": "4\u00d7dice if 1 owned, 10\u00d7dice if both owned",
    "8": "50",
    "9": "60",
    "10": "25 if 1 owned, 50 if 2 owned, 100 if 3 owned, 200 if all 4 owned",
    "11": "70",
    "12": "70",
    "13": "80",
    "14": "90",
    "15": "90",
    "16": "100",
    "17": "25 if 1 owned, 50 if 2 owned, 100 if 3 owned, 200 if all 4 owned",
    "18": "110",
    "19": "110",
    "20": "4\u00d7dice if 1 owned, 10\u00d7dice if both owned",
    "21": "120",
    "22": "130",
    "23": "130",
    "24": "150",
    "25": "25 if 1 owned, 50 if 2 owned, 100 if 3 owned, 200 if all 4 owned",
    "26": "175",
    "27": "200"
  },
  "('Rent', '2 houses')": {
    "0": "30",
    "1": "60",
    "2": "25 if 1 owned, 50 if 2 owned, 100 if 3 owned, 200 if all 4 owned",
    "3": "90",
    "4": "90",
    "5": "100",
    "6": "150",
    "7": "4\u00d7dice if 1 owned, 10\u00d7dice if both owned",
    "8": "150",
    "9": "180",
    "10": "25 if 1 owned, 50 if 2 owned, 100 if 3 owned, 200 if all 4 owned",
    "11": "200",
    "12": "200",
    "13": "220",
    "14": "250",
    "15": "250",
    "16": "300",
    "17": "25 if 1 owned, 50 if 2 owned, 100 if 3 owned, 200 if all 4 owned",
    "18": "330",
    "19": "330",
    "20": "4\u00d7dice if 1 owned, 10\u00d7dice if both owned",
    "21": "360",
    "22": "390",
    "23": "390",
    "24": "450",
    "25": "25 if 1 owned, 50 if 2 owned, 100 if 3 owned, 200 if all 4 owned",
    "26": "500",
    "27": "600"
  },
  "('Rent', '3 houses')": {
    "0": "90",
    "1": "180",
    "2": "25 if 1 owned, 50 if 2 owned, 100 if 3 owned, 200 if all 4 owned",
    "3": "270",
    "4": "270",
    "5": "300",
    "6": "450",
    "7": "4\u00d7dice if 1 owned, 10\u00d7dice if both owned",
    "8": "450",
    "9": "500",
    "10": "25 if 1 owned, 50 if 2 owned, 100 if 3 owned, 200 if all 4 owned",
    "11": "550",
    "12": "550",
    "13": "600",
    "14": "700",
    "15": "700",
    "16": "750",
    "17": "25 if 1 owned, 50 if 2 owned, 100 if 3 owned, 200 if all 4 owned",
    "18": "800",
    "19": "800",
    "20": "4\u00d7dice if 1 owned, 10\u00d7dice if both owned",
    "21": "850",
    "22": "900",
    "23": "900",
    "24": "1000",
    "25": "25 if 1 owned, 50 if 2 owned, 100 if 3 owned, 200 if all 4 owned",
    "26": "1100",
    "27": "1400"
  },
  "('Rent', '4 houses')": {
    "0": "160",
    "1": "320",
    "2": "25 if 1 owned, 50 if 2 owned, 100 if 3 owned, 200 if all 4 owned",
    "3": "400",
    "4": "400",
    "5": "450",
    "6": "625",
    "7": "4\u00d7dice if 1 owned, 10\u00d7dice if both owned",
    "8": "625",
    "9": "700",
    "10": "25 if 1 owned, 50 if 2 owned, 100 if 3 owned, 200 if all 4 owned",
    "11": "750",
    "12": "750",
    "13": "800",
    "14": "875",
    "15": "875",
    "16": "925",
    "17": "25 if 1 owned, 50 if 2 owned, 100 if 3 owned, 200 if all 4 owned",
    "18": "975",
    "19": "975",
    "20": "4\u00d7dice if 1 owned, 10\u00d7dice if both owned",
    "21": "1025",
    "22": "1100",
    "23": "1100",
    "24": "1200",
    "25": "25 if 1 owned, 50 if 2 owned, 100 if 3 owned, 200 if all 4 owned",
    "26": "1300",
    "27": "1700"
  },
  "('Rent', 'Hotel')": {
    "0": "250",
    "1": "450",
    "2": "25 if 1 owned, 50 if 2 owned, 100 if 3 owned, 200 if all 4 owned",
    "3": "550",
    "4": "550",
    "5": "600",
    "6": "750",
    "7": "4\u00d7dice if 1 owned, 10\u00d7dice if both owned",
    "8": "750",
    "9": "900",
    "10": "25 if 1 owned, 50 if 2 owned, 100 if 3 owned, 200 if all 4 owned",
    "11": "950",
    "12": "950",
    "13": "1000",
    "14": "1050",
    "15": "1050",
    "16": "1100",
    "17": "25 if 1 owned, 50 if 2 owned, 100 if 3 owned, 200 if all 4 owned",
    "18": "1150",
    "19": "1150",
    "20": "4\u00d7dice if 1 owned, 10\u00d7dice if both owned",
    "21": "1200",
    "22": "1275",
    "23": "1275",
    "24": "1400",
    "25": "25 if 1 owned, 50 if 2 owned, 100 if 3 owned, 200 if all 4 owned",
    "26": "1500",
    "27": "2000"
  }
}